odoo/addons/web_widget_bokeh_chart/README.rst
odoo/addons/web_widget_bokeh_chart/__init__.py
odoo/addons/web_widget_bokeh_chart/__manifest__.py
odoo/addons/web_widget_bokeh_chart/i18n/it.po
odoo/addons/web_widget_bokeh_chart/i18n/web_widget_bokeh_chart.pot
odoo/addons/web_widget_bokeh_chart/i18n/zh_CN.po
odoo/addons/web_widget_bokeh_chart/readme/CONTRIBUTORS.md
odoo/addons/web_widget_bokeh_chart/readme/CREDITS.md
odoo/addons/web_widget_bokeh_chart/readme/DESCRIPTION.md
odoo/addons/web_widget_bokeh_chart/readme/INSTALL.md
odoo/addons/web_widget_bokeh_chart/readme/ROADMAP.md
odoo/addons/web_widget_bokeh_chart/readme/USAGE.md
odoo/addons/web_widget_bokeh_chart/static/description/example.png
odoo/addons/web_widget_bokeh_chart/static/description/icon.png
odoo/addons/web_widget_bokeh_chart/static/description/index.html
odoo/addons/web_widget_bokeh_chart/static/src/js/web_widget_bokeh_chart.esm.js
odoo/addons/web_widget_bokeh_chart/static/src/js/web_widget_bokeh_json_chart.esm.js
odoo/addons/web_widget_bokeh_chart/static/src/lib/bokeh/bokeh-3.6.3.min.js
odoo/addons/web_widget_bokeh_chart/static/src/lib/bokeh/bokeh-api-3.6.3.min.js
odoo/addons/web_widget_bokeh_chart/static/src/lib/bokeh/bokeh-gl-3.6.3.min.js
odoo/addons/web_widget_bokeh_chart/static/src/lib/bokeh/bokeh-mathjax-3.6.3.min.js
odoo/addons/web_widget_bokeh_chart/static/src/lib/bokeh/bokeh-tables-3.6.3.min.js
odoo/addons/web_widget_bokeh_chart/static/src/lib/bokeh/bokeh-widgets-3.6.3.min.js
odoo/addons/web_widget_bokeh_chart/static/src/xml/bokeh.xml
odoo_addon_web_widget_bokeh_chart-18.0.1.0.1.dist-info/METADATA
odoo_addon_web_widget_bokeh_chart-18.0.1.0.1.dist-info/WHEEL
odoo_addon_web_widget_bokeh_chart-18.0.1.0.1.dist-info/top_level.txt
odoo_addon_web_widget_bokeh_chart-18.0.1.0.1.dist-info/RECORD
