Metadata-Version: 2.1
Name: odoo-addon-web_widget_bokeh_chart
Version: 18.0.1.0.1
Requires-Python: >=3.10
Requires-Dist: bokeh==3.6.3
Requires-Dist: odoo==18.0.*
Summary: This widget allows to display charts using Bokeh library.
Home-page: https://github.com/OCA/web
License: LGPL-3
Author: ForgeFlow, Odoo Community Association (OCA), Creu Blanca
Author-email: support@odoo-community.org
Classifier: Programming Language :: Python
Classifier: Framework :: Odoo
Classifier: Framework :: Odoo :: 18.0
Classifier: License :: OSI Approved :: GNU Lesser General Public License v3 (LGPLv3)
Classifier: Development Status :: 5 - Production/Stable
